{
  "left": {
    "tvId": "left",
    "rows": 3,
    "cols": 2,
    "timelines": [
      [
        1778746784092,
        1778746843424,
        1778746843884
      ],
      [
        1778746799219,
        1778746799629,
        1778746798859,
        1778746799115,
        1778746798836,
        1778746799244,
        1778746799817,
        1778746799049,
        1778746799040,
        1778746798910,
        1778746799502,
        1778746799815,
        1778746799130,
        1778746799387,
        1778746798912,
        1778746799706,
        1778746799757,
        1778746799225,
        1778746799637,
        1778746799491,
        1778746799045,
        1778746799708
      ],
      [
        1778746844231,
        1778746843645,
        1778746843682,
        1778746843884,
        1778746843483,
        1778746843998,
        1778746843758,
        1778746843424
      ]
    ],
    "rowAnimationModes": [
      "strip",
      "strip",
      "strip"
    ],
    "rowSteps": [
      1,
      1,
      1
    ],
    "stripSteps": [
      2,
      2,
      2
    ],
    "rowCellGaps": [
      4,
      4,
      4
    ],
    "rowOffsets": [
      0,
      2000,
      4000
    ],
    "cellGap": 4,
    "rotation": -90,
    "rowLabels": [
      "",
      "",
      ""
    ],
    "timelineSpans": [
      [
        2,
        1,
        1
      ],
      [
        1,
        1,
        1,
        1,
        1,
        1,
        1,
        1,
        1,
        1,
        1,
        1,
        1,
        1,
        1,
        1,
        1,
        1,
        1,
        1,
        1,
        1
      ],
      [
        1,
        1,
        1,
        1,
        1,
        1,
        1,
        1
      ]
    ]
  },
  "right": {
    "tvId": "right",
    "rows": 2,
    "cols": 3,
    "timelines": [
      [
        1778705926351,
        1778705926574,
        1778705926728,
        1778705926844,
        1778705926375,
        1778705926269
      ],
      [
        1778705927056,
        1778705927166,
        1778705927130,
        1778705927167,
        1778705926569,
        1778705927222
      ]
    ],
    "rowAnimationModes": [
      "strip",
      "strip"
    ],
    "rowSteps": [
      1,
      1
    ],
    "stripSteps": [
      3,
      4
    ],
    "rowCellGaps": [
      4,
      4
    ],
    "rowOffsets": [
      0,
      2000
    ],
    "cellGap": 4,
    "rotation": 0
  }
}